[{"id_": "1068337838", "raw_data": {"id": 1068337838, "id_str": "1068337838", "name": "Luisa Neubauer", "screen_name": "Luisamneubauer", "location": "Berlin, Germany", "description": "climate activist #fridaysforfuture • student • author • podcast host • born 364 ppm ✉️contact.luisa.neubauer@gmail.com", "url": "https://t.co/VFs2QRt9Mq", "entities": {"url": {"urls": [{"url": "https://t.co/VFs2QRt9Mq", "expanded_url": "http://luisaneubauer.com", "display_url": "luisaneubauer.com", "indices": [0, 23]}]}, "description": {"urls": []}}, "protected": false, "followers_count": 199312, "fast_followers_count": 0, "normal_followers_count": 199312, "friends_count": 1279, "listed_count": 886, "created_at": "Mon Jan 07 13:38:44 +0000 2013", "favourites_count": 12930, "utc_offset": null, "time_zone": null, "geo_enabled": true, "verified": true, "statuses_count": 3750, "media_count": 283, "lang": null, "contributors_enabled": false, "is_translator": false, "is_translation_enabled": false, "profile_background_color": "022330", "profile_background_image_url": "http://abs.twimg.com/images/themes/theme15/bg.png", "profile_background_image_url_https": "https://abs.twimg.com/images/themes/theme15/bg.png", "profile_background_tile": false, "profile_image_url": "http://pbs.twimg.com/profile_images/1311356595163586562/m7xElFy-_normal.jpg", "profile_image_url_https": "https://pbs.twimg.com/profile_images/1311356595163586562/m7xElFy-_normal.jpg", "profile_banner_url": "https://pbs.twimg.com/profile_banners/1068337838/1598696806", "profile_image_extensions_alt_text": null, "profile_image_extensions_media_availability": null, "profile_image_extensions_media_color": {"palette": [{"rgb": {"red": 157, "green": 143, "blue": 132}, "percentage": 52.54}, {"rgb": {"red": 58, "green": 41, "blue": 35}, "percentage": 35.89}, {"rgb": {"red": 134, "green": 97, "blue": 86}, "percentage": 0.2}]}, "profile_image_extensions": {"mediaStats": {"r": {"missing": null}, "ttl": -1}}, "profile_banner_extensions_alt_text": null, "profile_banner_extensions_media_availability": null, "profile_banner_extensions_media_color": {"palette": [{"rgb": {"red": 54, "green": 40, "blue": 31}, "percentage": 57.38}, {"rgb": {"red": 180, "green": 174, "blue": 173}, "percentage": 20.46}, {"rgb": {"red": 125, "green": 99, "blue": 86}, "percentage": 8.3}, {"rgb": {"red": 97, "green": 72, "blue": 46}, "percentage": 4.85}, {"rgb": {"red": 200, "green": 173, "blue": 141}, "percentage": 1.47}]}, "profile_banner_extensions": {"mediaStats": {"r": {"missing": null}, "ttl": -1}}, "profile_link_color": "0084B4", "profile_sidebar_border_color": "A8C7F7", "profile_sidebar_fill_color": "C0DFEC", "profile_text_color": "333333", "profile_use_background_image": true, "has_extended_profile": true, "default_profile": false, "default_profile_image": false, "pinned_tweet_ids": [1349395088074485760], "pinned_tweet_ids_str": ["1349395088074485760"], "has_custom_timelines": true, "can_dm": null, "following": null, "follow_request_sent": null, "notifications": null, "muting": null, "blocking": null, "blocked_by": null, "want_retweets": null, "advertiser_account_type": "promotable_user", "advertiser_account_service_levels": ["analytics"], "profile_interstitial_type": "", "business_profile_state": "none", "translator_type": "none", "followed_by": null, "ext": {"highlightedLabel": {"r": {"ok": {}}, "ttl": -1}}, "require_some_consent": false}}, {"id_": "22926365", "raw_data": {"id": 22926365, "id_str": "22926365", "name": "Tagesspiegel", "screen_name": "Tagesspiegel", "location": "Berlin", "description": "Das Leitmedium der Hauptstadt. 📰", "url": "https://t.co/gAjTXHhkYD", "entities": {"url": {"urls": [{"url": "https://t.co/gAjTXHhkYD", "expanded_url": "https://www.tagesspiegel.de", "display_url": "tagesspiegel.de", "indices": [0, 23]}]}, "description": {"urls": []}}, "protected": false, "followers_count": 430510, "fast_followers_count": 0, "normal_followers_count": 430510, "friends_count": 1499, "listed_count": 3996, "created_at": "Thu Mar 05 14:47:03 +0000 2009", "favourites_count": 6913, "utc_offset": null, "time_zone": null, "geo_enabled": false, "verified": true, "statuses_count": 253318, "media_count": 25426, "lang": null, "contributors_enabled": false, "is_translator": false, "is_translation_enabled": false, "profile_background_color": "FFFFFF", "profile_background_image_url": "http://abs.twimg.com/images/themes/theme1/bg.png", "profile_background_image_url_https": "https://abs.twimg.com/images/themes/theme1/bg.png", "profile_background_tile": false, "profile_image_url": "http://pbs.twimg.com/profile_images/989224444152504320/a06BJJ2y_normal.jpg", "profile_image_url_https": "https://pbs.twimg.com/profile_images/989224444152504320/a06BJJ2y_normal.jpg", "profile_banner_url": "https://pbs.twimg.com/profile_banners/22926365/1527165587", "profile_image_extensions_alt_text": null, "profile_image_extensions_media_availability": null, "profile_image_extensions_media_color": {"palette": [{"rgb": {"red": 255, "green": 255, "blue": 255}, "percentage": 78.85}, {"rgb": {"red": 0, "green": 0, "blue": 0}, "percentage": 13.91}, {"rgb": {"red": 187, "green": 44, "blue": 12}, "percentage": 2.51}, {"rgb": {"red": 222, "green": 147, "blue": 128}, "percentage": 1.53}, {"rgb": {"red": 194, "green": 40, "blue": 12}, "percentage": 0.1}]}, "profile_image_extensions": {"mediaStats": {"r": {"missing": null}, "ttl": -1}}, "profile_banner_extensions_media_color": {"palette": [{"rgb": {"red": 188, "green": 177, "blue": 191}, "percentage": 50.47}, {"rgb": {"red": 103, "green": 58, "blue": 107}, "percentage": 10.9}, {"rgb": {"red": 56, "green": 52, "blue": 64}, "percentage": 8.27}, {"rgb": {"red": 111, "green": 59, "blue": 60}, "percentage": 6.14}, {"rgb": {"red": 158, "green": 32, "blue": 80}, "percentage": 2.82}]}, "profile_banner_extensions_alt_text": null, "profile_banner_extensions_media_availability": null, "profile_banner_extensions": {"mediaStats": {"r": {"missing": null}, "ttl": -1}}, "profile_link_color": "CE0000", "profile_sidebar_border_color": "FFFFFF", "profile_sidebar_fill_color": "F3F2F2", "profile_text_color": "333333", "profile_use_background_image": true, "has_extended_profile": true, "default_profile": false, "default_profile_image": false, "pinned_tweet_ids": [1352115077252591620], "pinned_tweet_ids_str": ["1352115077252591620"], "has_custom_timelines": true, "can_dm": null, "following": null, "follow_request_sent": null, "notifications": null, "muting": null, "blocking": null, "blocked_by": null, "want_retweets": null, "advertiser_account_type": "promotable_user", "advertiser_account_service_levels": ["smb", "media_studio"], "profile_interstitial_type": "", "business_profile_state": "none", "translator_type": "none", "followed_by": null, "ext": {"highlightedLabel": {"r": {"ok": {}}, "ttl": -1}}, "require_some_consent": false}}, {"id_": "288696645", "raw_data": {"id": 288696645, "id_str": "288696645", "name": "Paul Ziemiak", "screen_name": "PaulZiemiak", "location": "Germany", "description": "Generalsekretär der @cdu I🇩🇪MdB | 🏡 Iserlohner", "url": "https://t.co/Euh6GvHMyA", "entities": {"url": {"urls": [{"url": "https://t.co/Euh6GvHMyA", "expanded_url": "https://www.bundestag.de/abgeordnete/biografien/Z/ziemiak_paul-524780", "display_url": "bundestag.de/abgeordnete/bi…", "indices": [0, 23]}]}, "description": {"urls": []}}, "protected": false, "followers_count": 41407, "fast_followers_count": 0, "normal_followers_count": 41407, "friends_count": 636, "listed_count": 339, "created_at": "Wed Apr 27 09:22:47 +0000 2011", "favourites_count": 3549, "utc_offset": null, "time_zone": null, "geo_enabled": true, "verified": true, "statuses_count": 4907, "media_count": 1148, "lang": null, "contributors_enabled": false, "is_translator": false, "is_translation_enabled": false, "profile_background_color": "0099B9", "profile_background_image_url": "http://abs.twimg.com/images/themes/theme15/bg.png", "profile_background_image_url_https": "https://abs.twimg.com/images/themes/theme15/bg.png", "profile_background_tile": false, "profile_image_url": "http://pbs.twimg.com/profile_images/1351125296309805060/_teavRmh_normal.jpg", "profile_image_url_https": "https://pbs.twimg.com/profile_images/1351125296309805060/_teavRmh_normal.jpg", "profile_banner_url": "https://pbs.twimg.com/profile_banners/288696645/1580153150", "profile_image_extensions_alt_text": null, "profile_image_extensions_media_availability": null, "profile_image_extensions_media_color": {"palette": [{"rgb": {"red": 210, "green": 210, "blue": 195}, "percentage": 40.16}, {"rgb": {"red": 36, "green": 53, "blue": 76}, "percentage": 22.04}, {"rgb": {"red": 116, "green": 120, "blue": 105}, "percentage": 13.61}, {"rgb": {"red": 195, "green": 213, "blue": 238}, "percentage": 3.86}, {"rgb": {"red": 183, "green": 188, "blue": 136}, "percentage": 3.85}]}, "profile_image_extensions": {"mediaStats": {"r": {"missing": null}, "ttl": -1}}, "profile_banner_extensions_alt_text": null, "profile_banner_extensions_media_availability": null, "profile_banner_extensions_media_color": {"palette": [{"rgb": {"red": 34, "green": 28, "blue": 24}, "percentage": 76.33}, {"rgb": {"red": 35, "green": 57, "blue": 68}, "percentage": 7.69}, {"rgb": {"red": 155, "green": 157, "blue": 165}, "percentage": 6.47}, {"rgb": {"red": 82, "green": 49, "blue": 40}, "percentage": 3.18}, {"rgb": {"red": 1, "green": 65, "blue": 117}, "percentage": 0.64}]}, "profile_banner_extensions": {"mediaStats": {"r": {"missing": null}, "ttl": -1}}, "profile_link_color": "3B94D9", "profile_sidebar_border_color": "FFFFFF", "profile_sidebar_fill_color": "C0DFEC", "profile_text_color": "333333", "profile_use_background_image": false, "has_extended_profile": true, "default_profile": false, "default_profile_image": false, "pinned_tweet_ids": [1191996462382669825], "pinned_tweet_ids_str": ["1191996462382669825"], "has_custom_timelines": false, "can_dm": null, "following": null, "follow_request_sent": null, "notifications": null, "muting": null, "blocking": null, "blocked_by": null, "want_retweets": null, "advertiser_account_type": "promotable_user", "advertiser_account_service_levels": [], "profile_interstitial_type": "", "business_profile_state": "none", "translator_type": "none", "followed_by": null, "ext": {"highlightedLabel": {"r": {"ok": {}}, "ttl": -1}}, "require_some_consent": false}}, {"id_": "3188225915", "raw_data": {"id": 3188225915, "id_str": "3188225915", "name": "Torbjörn Kartes", "screen_name": "KartesMdB", "location": "", "description": "Mitglied des Deutschen Bundestages, direkt gewählt von den Menschen in Ludwigshafen, Frankenthal und den Rhein-Pfalz-Kreis, Ehemann und stolzer Papa", "url": "https://t.co/Any2MF42Bo", "entities": {"url": {"urls": [{"url": "https://t.co/Any2MF42Bo", "expanded_url": "http://www.torbjoern-kartes.de", "display_url": "torbjoern-kartes.de", "indices": [0, 23]}]}, "description": {"urls": []}}, "protected": false, "followers_count": 732, "fast_followers_count": 0, "normal_followers_count": 732, "friends_count": 430, "listed_count": 50, "created_at": "Mon Apr 20 20:23:44 +0000 2015", "favourites_count": 515, "utc_offset": null, "time_zone": null, "geo_enabled": true, "verified": true, "statuses_count": 397, "media_count": 63, "lang": null, "contributors_enabled": false, "is_translator": false, "is_translation_enabled": false, "profile_background_color": "C0DEED", "profile_background_image_url": "http://abs.twimg.com/images/themes/theme1/bg.png", "profile_background_image_url_https": "https://abs.twimg.com/images/themes/theme1/bg.png", "profile_background_tile": false, "profile_image_url": "http://pbs.twimg.com/profile_images/1290945579787456513/DmFjblh9_normal.jpg", "profile_image_url_https": "https://pbs.twimg.com/profile_images/1290945579787456513/DmFjblh9_normal.jpg", "profile_banner_url": "https://pbs.twimg.com/profile_banners/3188225915/1596714826", "profile_image_extensions_alt_text": null, "profile_image_extensions_media_availability": null, "profile_image_extensions_media_color": {"palette": [{"rgb": {"red": 168, "green": 172, "blue": 173}, "percentage": 39.67}, {"rgb": {"red": 41, "green": 48, "blue": 52}, "percentage": 38.65}, {"rgb": {"red": 219, "green": 172, "blue": 155}, "percentage": 7.36}, {"rgb": {"red": 100, "green": 112, "blue": 128}, "percentage": 4.51}, {"rgb": {"red": 53, "green": 43, "blue": 28}, "percentage": 2.9}]}, "profile_image_extensions": {"mediaStats": {"r": {"missing": null}, "ttl": -1}}, "profile_banner_extensions_alt_text": null, "profile_banner_extensions_media_availability": null, "profile_banner_extensions_media_color": {"palette": [{"rgb": {"red": 224, "green": 220, "blue": 217}, "percentage": 70.06}, {"rgb": {"red": 114, "green": 118, "blue": 118}, "percentage": 11.7}, {"rgb": {"red": 51, "green": 61, "blue": 67}, "percentage": 10.39}, {"rgb": {"red": 217, "green": 204, "blue": 174}, "percentage": 2.83}, {"rgb": {"red": 193, "green": 147, "blue": 133}, "percentage": 1.22}]}, "profile_banner_extensions": {"mediaStats": {"r": {"missing": null}, "ttl": -1}}, "profile_link_color": "1DA1F2", "profile_sidebar_border_color": "C0DEED", "profile_sidebar_fill_color": "DDEEF6", "profile_text_color": "333333", "profile_use_background_image": true, "has_extended_profile": true, "default_profile": true, "default_profile_image": false, "pinned_tweet_ids": [], "pinned_tweet_ids_str": [], "has_custom_timelines": false, "can_dm": null, "following": null, "follow_request_sent": null, "notifications": null, "muting": null, "blocking": null, "blocked_by": null, "want_retweets": null, "advertiser_account_type": "promotable_user", "advertiser_account_service_levels": [], "profile_interstitial_type": "", "business_profile_state": "none", "translator_type": "none", "followed_by": null, "ext": {"highlightedLabel": {"r": {"ok": {}}, "ttl": -1}}, "require_some_consent": false}}]